finscreen/__init__.py
finscreen/finscreen.py
finscreen-0.1.1.dist-info/METADATA
finscreen-0.1.1.dist-info/WHEEL
finscreen-0.1.1.dist-info/top_level.txt
finscreen-0.1.1.dist-info/RECORD
