Metadata-Version: 2.1
Name: finscreen
Version: 0.1.1
Summary: Screen stocks on FinViz and scrape the data into dataframe.
Home-page: https://github.com/Haarth/finscreen
Author: haarthiel
Author-email: <haarthiel@gmail.com>
License: UNKNOWN
Keywords: python,finviz,scraper,stock screening
Platform: UNKNOWN
Classifier: Development Status :: 1 - Planning
Classifier: Intended Audience :: Financial and Insurance Industry
Classifier: Programming Language :: Python :: 3.9
Classifier: Operating System :: Unix
Classifier: Operating System :: MacOS :: MacOS X
Classifier: Operating System :: Microsoft :: Windows
Requires-Dist: pandas
Requires-Dist: tqdm
Requires-Dist: requests
